[
    {
        "Xw": 178344.8925292064,
        "Yw": 211112.0247531787,
        "Zw": 0.0,
        "object_size": [
            1.6127057075500488,
            0.5400301218032837,
            0.40389835834503174
        ],
        "personID": 33,
        "rotation_theta": 3.1110082149530958,
        "rectangleID": "3f0788b0ea2f"
    },
    {
        "Xw": 178350.0543638859,
        "Yw": 211113.40869604156,
        "Zw": 0.0,
        "object_size": [
            1.880278468132019,
            0.4670768976211548,
            0.21569368243217468
        ],
        "personID": 129,
        "rotation_theta": 1.5003206469484982,
        "rectangleID": "f785742ae052"
    },
    {
        "Xw": 178342.96133474537,
        "Yw": 211122.98797512718,
        "Zw": 0.0,
        "object_size": [
            1.7258868217468262,
            0.5171512961387634,
            0.5344916582107544
        ],
        "personID": 426,
        "rotation_theta": 0.8271213019273693,
        "rectangleID": "5a4f5609be47"
    },
    {
        "Xw": 178336.5214752481,
        "Yw": 211114.58146645437,
        "Zw": 0.0,
        "object_size": [
            1.6135472059249878,
            0.2588856518268585,
            0.4812922179698944
        ],
        "personID": 483,
        "rotation_theta": 2.0060326440906127,
        "rectangleID": "67c2a511ca15"
    },
    {
        "Xw": 178345.4691012852,
        "Yw": 211109.61520421508,
        "Zw": 0.0,
        "object_size": [
            1.6298283338546753,
            0.4832940399646759,
            0.20181572437286377
        ],
        "personID": 496,
        "rotation_theta": 0.5080312176272944,
        "rectangleID": "a1ebccbcc939"
    },
    {
        "Xw": 178334.75072153247,
        "Yw": 211117.90381813294,
        "Zw": 0.0,
        "object_size": [
            1.8310661315917969,
            0.46784132719039917,
            0.2503003776073456
        ],
        "personID": 503,
        "rotation_theta": 2.263825991704652,
        "rectangleID": "cb5bf32b4fb0"
    },
    {
        "Xw": 178334.15867534143,
        "Yw": 211114.0089349086,
        "Zw": 0.0,
        "object_size": [
            1.9181780815124512,
            0.47810521721839905,
            0.31829604506492615
        ],
        "personID": 550,
        "rotation_theta": 0.4756215490805898,
        "rectangleID": "9e882721f63a"
    },
    {
        "Xw": 178351.90266311515,
        "Yw": 211115.07491094118,
        "Zw": 0.0,
        "object_size": [
            1.823119878768921,
            0.28905409574508667,
            0.49684831500053406
        ],
        "personID": 602,
        "rotation_theta": 0.015646509234379675,
        "rectangleID": "d22a17e979cc"
    },
    {
        "Xw": 178335.39242379018,
        "Yw": 211121.53533103334,
        "Zw": 0.0,
        "object_size": [
            1.7767690420150757,
            0.4503871500492096,
            0.2858564257621765
        ],
        "personID": 727,
        "rotation_theta": 2.640330829686679,
        "rectangleID": "3a5efa646c83"
    },
    {
        "Xw": 178341.1820283371,
        "Yw": 211124.45038203616,
        "Zw": 0.0,
        "object_size": [
            1.9698151350021362,
            0.5001810193061829,
            0.4999977946281433
        ],
        "personID": 771,
        "rotation_theta": 1.2059801840344253,
        "rectangleID": "477b2d127288"
    },
    {
        "Xw": 178350.67169289436,
        "Yw": 211110.49661539152,
        "Zw": 0.0,
        "object_size": [
            1.7668572664260864,
            0.2798851430416107,
            0.49606725573539734
        ],
        "personID": 790,
        "rotation_theta": 2.6721324195496363,
        "rectangleID": "94a46bc31b50"
    },
    {
        "Xw": 178342.76085320924,
        "Yw": 211118.91606825317,
        "Zw": 0.0,
        "object_size": [
            1.8131740093231201,
            0.46068260073661804,
            0.49403947591781616
        ],
        "personID": 815,
        "rotation_theta": 0.28776790595096285,
        "rectangleID": "130421d2f8d2"
    },
    {
        "Xw": 178335.59041865845,
        "Yw": 211120.2763167391,
        "Zw": 0.0,
        "object_size": [
            1.9074379205703735,
            0.49754828214645386,
            0.4828208386898041
        ],
        "personID": 837,
        "rotation_theta": 0.7562618607075206,
        "rectangleID": "f53c6957f614"
    },
    {
        "Xw": 178331.06875701615,
        "Yw": 211119.52174364714,
        "Zw": 0.0,
        "object_size": [
            1.7223562002182007,
            0.4961555302143097,
            0.49130597710609436
        ],
        "personID": 844,
        "rotation_theta": 3.0190588731704993,
        "rectangleID": "c69b07544f35"
    },
    {
        "Xw": 178334.66471969784,
        "Yw": 211120.98623190526,
        "Zw": 0.0,
        "object_size": [
            1.954150915145874,
            0.49944162368774414,
            0.49435505270957947
        ],
        "personID": 861,
        "rotation_theta": 0.742164465138748,
        "rectangleID": "12b7df012474"
    },
    {
        "Xw": 178356.62055046216,
        "Yw": 211108.9889355361,
        "Zw": 0.0,
        "object_size": [
            0.8150590658187866,
            0.4748964011669159,
            0.20168332755565643
        ],
        "personID": 78,
        "rotation_theta": 2.720581592156065,
        "rectangleID": "5ec61406b342"
    },
    {
        "Xw": 178359.62067038848,
        "Yw": 211108.44133936084,
        "Zw": 0.0,
        "object_size": [
            1.7493855953216553,
            0.2565758228302002,
            0.26377031207084656
        ],
        "personID": 173,
        "rotation_theta": 0.507603423578473,
        "rectangleID": "3e155d730b9d"
    },
    {
        "Xw": 178354.0774127893,
        "Yw": 211110.40495343067,
        "Zw": 0.0,
        "object_size": [
            1.9484295845031738,
            0.4508328437805176,
            0.5602675080299377
        ],
        "personID": 489,
        "rotation_theta": 2.268364721746303,
        "rectangleID": "3d3366e8dae1"
    },
    {
        "Xw": 178356.6212185178,
        "Yw": 211109.83415657608,
        "Zw": 0.0,
        "object_size": [
            1.6954419612884521,
            0.44026997685432434,
            0.44348031282424927
        ],
        "personID": 561,
        "rotation_theta": 2.376053671489209,
        "rectangleID": "3de25632e675"
    },
    {
        "Xw": 178353.9767117757,
        "Yw": 211112.9093534389,
        "Zw": 0.0,
        "object_size": [
            1.7996511459350586,
            0.4802697002887726,
            0.3681025505065918
        ],
        "personID": 830,
        "rotation_theta": 2.103659346809379,
        "rectangleID": "46770cdf0a0c"
    },
    {
        "Xw": 178353.80108802,
        "Yw": 211108.47540550423,
        "Zw": 0.0,
        "object_size": [
            1.6175020933151245,
            0.29998305439949036,
            0.5773376822471619
        ],
        "personID": 841,
        "rotation_theta": 2.488734369580557,
        "rectangleID": "91ce881c040a"
    },
    {
        "Xw": 178353.46628064464,
        "Yw": 211113.32596992768,
        "Zw": 0.0,
        "object_size": [
            1.727602243423462,
            0.5557509064674377,
            0.38744449615478516
        ],
        "personID": 852,
        "rotation_theta": 2.11576787399616,
        "rectangleID": "16060e710d1d"
    },
    {
        "Xw": 178358.01228042587,
        "Yw": 211099.70121995884,
        "Zw": 0.0,
        "object_size": [
            1.0364017486572266,
            0.8372989892959595,
            0.47239020466804504
        ],
        "personID": 6,
        "rotation_theta": 2.267661265981546,
        "rectangleID": "b205b3005df0"
    },
    {
        "Xw": 178358.85514212612,
        "Yw": 211097.06216487018,
        "Zw": 0.0,
        "object_size": [
            1.70444655418396,
            0.5611264109611511,
            0.48411867022514343
        ],
        "personID": 204,
        "rotation_theta": 0.9614422947772429,
        "rectangleID": "b4bf2fb47883"
    },
    {
        "Xw": 178362.76713302732,
        "Yw": 211101.02694807274,
        "Zw": 0.0,
        "object_size": [
            1.6781021356582642,
            0.3941662311553955,
            0.2626623809337616
        ],
        "personID": 401,
        "rotation_theta": 0.628637109990012,
        "rectangleID": "2188689abdc5"
    },
    {
        "Xw": 178358.30889132322,
        "Yw": 211103.03088312672,
        "Zw": 0.0,
        "object_size": [
            1.4977631568908691,
            0.32449138164520264,
            0.5097731351852417
        ],
        "personID": 403,
        "rotation_theta": 2.0628267149796424,
        "rectangleID": "4909a5471419"
    },
    {
        "Xw": 178368.60828062333,
        "Yw": 211090.1168308841,
        "Zw": 0.0,
        "object_size": [
            1.7226529121398926,
            0.4216512441635132,
            0.4541405141353607
        ],
        "personID": 432,
        "rotation_theta": 2.1810614357348332,
        "rectangleID": "d23f1f6755b2"
    },
    {
        "Xw": 178373.73683943824,
        "Yw": 211068.887677016,
        "Zw": 0.0,
        "object_size": [
            1.879763126373291,
            0.5831412076950073,
            0.20376843214035034
        ],
        "personID": 532,
        "rotation_theta": 1.7531188720091575,
        "rectangleID": "d5b3fcd7b876"
    },
    {
        "Xw": 178358.1303295906,
        "Yw": 211102.29988885598,
        "Zw": 0.0,
        "object_size": [
            1.5538337230682373,
            0.5132208466529846,
            0.34809380769729614
        ],
        "personID": 633,
        "rotation_theta": 0.5651620595811194,
        "rectangleID": "afd2ffff759f"
    },
    {
        "Xw": 178351.2540003578,
        "Yw": 211100.62355757266,
        "Zw": 0.0,
        "object_size": [
            1.4950207471847534,
            0.4807310700416565,
            0.31430596113204956
        ],
        "personID": 679,
        "rotation_theta": 1.4298398931792902,
        "rectangleID": "25d58782b7f7"
    },
    {
        "Xw": 178372.0421243814,
        "Yw": 211071.25739647826,
        "Zw": 0.0,
        "object_size": [
            1.9144842624664307,
            0.1680457592010498,
            0.47428858280181885
        ],
        "personID": 689,
        "rotation_theta": 0.2714298987426997,
        "rectangleID": "5248ad52bd9d"
    },
    {
        "Xw": 178376.00971953833,
        "Yw": 211077.4804682453,
        "Zw": 0.0,
        "object_size": [
            1.8753349781036377,
            0.4921709895133972,
            0.4775538444519043
        ],
        "personID": 695,
        "rotation_theta": 2.5371826793772896,
        "rectangleID": "a3f371d0b92e"
    },
    {
        "Xw": 178362.31809383287,
        "Yw": 211099.9056235691,
        "Zw": 0.0,
        "object_size": [
            1.7540041208267212,
            0.48269006609916687,
            0.32550743222236633
        ],
        "personID": 716,
        "rotation_theta": 0.6714313384544092,
        "rectangleID": "dc40b4828e41"
    },
    {
        "Xw": 178376.57651253295,
        "Yw": 211085.2325345405,
        "Zw": 0.0,
        "object_size": [
            1.5477385520935059,
            0.36243125796318054,
            0.4046841859817505
        ],
        "personID": 745,
        "rotation_theta": 2.9159591222716252,
        "rectangleID": "5bf7f393e318"
    },
    {
        "Xw": 178381.2872392124,
        "Yw": 211094.32112441913,
        "Zw": 0.0,
        "object_size": [
            1.8545243740081787,
            0.4921979010105133,
            0.4142223000526428
        ],
        "personID": 762,
        "rotation_theta": 2.417283047876599,
        "rectangleID": "89c7ebf6f233"
    },
    {
        "Xw": 178373.20075415343,
        "Yw": 211089.39525636833,
        "Zw": 0.0,
        "object_size": [
            1.5755281448364258,
            0.3270989954471588,
            0.4068062901496887
        ],
        "personID": 773,
        "rotation_theta": 2.789260676955584,
        "rectangleID": "c27a1dcce39e"
    },
    {
        "Xw": 178374.72547237494,
        "Yw": 211091.02925847674,
        "Zw": 0.0,
        "object_size": [
            1.714094638824463,
            0.48078474402427673,
            0.32668712735176086
        ],
        "personID": 800,
        "rotation_theta": 0.826682389579241,
        "rectangleID": "e39ce228914d"
    },
    {
        "Xw": 178376.56074696218,
        "Yw": 211078.0708665466,
        "Zw": 0.0,
        "object_size": [
            1.8402295112609863,
            0.4540804326534271,
            0.5495848059654236
        ],
        "personID": 804,
        "rotation_theta": 2.442755312695444,
        "rectangleID": "f1bc385e5ce6"
    },
    {
        "Xw": 178377.85460450326,
        "Yw": 211084.69831062775,
        "Zw": 0.0,
        "object_size": [
            1.758115291595459,
            0.48607203364372253,
            0.46069028973579407
        ],
        "personID": 806,
        "rotation_theta": 2.9563610763506754,
        "rectangleID": "1d122e970482"
    },
    {
        "Xw": 178374.3196719909,
        "Yw": 211088.84066032027,
        "Zw": 0.0,
        "object_size": [
            1.457118034362793,
            0.4472987651824951,
            0.4519408643245697
        ],
        "personID": 811,
        "rotation_theta": 2.093458738589492,
        "rectangleID": "833ee48de56e"
    },
    {
        "Xw": 178355.70922053728,
        "Yw": 211101.6672994308,
        "Zw": 0.0,
        "object_size": [
            1.703307867050171,
            0.4483722746372223,
            0.35645875334739685
        ],
        "personID": 819,
        "rotation_theta": 1.4983638492358704,
        "rectangleID": "eab42b86691e"
    },
    {
        "Xw": 178377.46777209203,
        "Yw": 211078.58354694495,
        "Zw": 0.0,
        "object_size": [
            1.9309850931167603,
            0.4939042925834656,
            0.49405792355537415
        ],
        "personID": 824,
        "rotation_theta": 2.250966207060156,
        "rectangleID": "c8645f4feedc"
    },
    {
        "Xw": 178375.17310381317,
        "Yw": 211085.6169806859,
        "Zw": 0.0,
        "object_size": [
            1.618813395500183,
            0.4208064675331116,
            0.4514752924442291
        ],
        "personID": 828,
        "rotation_theta": 2.8723835319301356,
        "rectangleID": "9b877e640fb8"
    },
    {
        "Xw": 178376.14607491862,
        "Yw": 211082.0981209529,
        "Zw": 0.0,
        "object_size": [
            1.7940226793289185,
            0.366463303565979,
            0.39529097080230713
        ],
        "personID": 831,
        "rotation_theta": 2.868718957132688,
        "rectangleID": "222113c61b2b"
    },
    {
        "Xw": 178361.93582019382,
        "Yw": 211085.99293850444,
        "Zw": 0.0,
        "object_size": [
            1.418967604637146,
            0.45743465423583984,
            0.4969482123851776
        ],
        "personID": 851,
        "rotation_theta": 1.6549552160602308,
        "rectangleID": "ddb98a45cf6d"
    },
    {
        "Xw": 178367.8040671804,
        "Yw": 211096.1705938859,
        "Zw": 0.0,
        "object_size": [
            1.5322223901748657,
            0.44541695713996887,
            0.31197306513786316
        ],
        "personID": 853,
        "rotation_theta": 1.3181639258248712,
        "rectangleID": "0d8ca55d27b2"
    },
    {
        "Xw": 178381.42434228887,
        "Yw": 211093.39266316599,
        "Zw": 0.0,
        "object_size": [
            1.9463974237442017,
            0.49617576599121094,
            0.46876007318496704
        ],
        "personID": 854,
        "rotation_theta": 2.522213455883381,
        "rectangleID": "abd318e33605"
    },
    {
        "Xw": 178385.24182390014,
        "Yw": 211067.01885290473,
        "Zw": 0.0,
        "object_size": [
            1.671871304512024,
            0.49898654222488403,
            0.4916937053203583
        ],
        "personID": 857,
        "rotation_theta": 2.2629346296305335,
        "rectangleID": "4dfdffb28633"
    },
    {
        "Xw": 178385.95956684643,
        "Yw": 211067.8676086506,
        "Zw": 0.0,
        "object_size": [
            1.5365784168243408,
            0.4983898997306824,
            0.4902316629886627
        ],
        "personID": 858,
        "rotation_theta": 2.3257670972403295,
        "rectangleID": "6f242e8c6931"
    },
    {
        "Xw": 178333.86645265165,
        "Yw": 211113.50731584043,
        "Zw": 0.0,
        "object_size": [
            1.838097095489502,
            0.5001310110092163,
            0.4993039071559906
        ],
        "personID": 855,
        "rotation_theta": 0.42089859749581576,
        "rectangleID": "971f40955b29"
    }
]